README.md
setup.py
bluetorch/__init__.py
bluetorch.egg-info/PKG-INFO
bluetorch.egg-info/SOURCES.txt
bluetorch.egg-info/dependency_links.txt
bluetorch.egg-info/not-zip-safe
bluetorch.egg-info/top_level.txt
bluetorch/base/__init__.py
bluetorch/base/base_data_loader.py
bluetorch/base/base_model.py
bluetorch/base/base_trainer.py
bluetorch/experiment/__init__.py
bluetorch/experiment/base_experiment.py
bluetorch/experiment/experiment_util.py
bluetorch/logger/__init__.py
bluetorch/logger/base_logger.py
bluetorch/saver/base_saver.py