Metadata-Version: 1.0
Name: bluetorch
Version: 0.111
Summary: Pytorch Blue Print for Research Project
Home-page: https://github.com/dspoka/bluetorch.git
Author: Daniel Spokoyny
Author-email: dspoka@gmail.com
License: MIT
Platform: UNKNOWN
